andisdk/SmartBind-Server.WibuCmLif
andisdk/__init__.py
andisdk/__init__.pyi
andisdk/_andi_docs.pyi
andisdk/autosar.py
andisdk/can.py
andisdk/debug.py
andisdk/e2e.py
andisdk/filters.py
andisdk/filters.pyi
andisdk/isotp.py
andisdk/modules.py
andisdk/program.py
andisdk/ptp.py
andisdk/runtimeconfig.json
andisdk/someip.py
andisdk/ssh.py
andisdk/tecmp.py
andisdk/converters/__init__.py
andisdk/converters/andisdk_converter.py
andisdk/converters/tecmp_converter.py
andisdk/converters/utils.py
andisdk/dlls/ANDi.Docs.deps.json
andisdk/dlls/ANDi.Docs.dll
andisdk/dlls/ANDi.Docs.exe
andisdk/dlls/ANDi.Docs.runtimeconfig.json
andisdk/dlls/ANDi.deps.json
andisdk/dlls/ANDi.dll
andisdk/dlls/AuthenticodeExaminer.dll
andisdk/dlls/CHANGELOG.htm
andisdk/dlls/Castle.Core.dll
andisdk/dlls/ClosedXML.dll
andisdk/dlls/DocumentFormat.OpenXml.dll
andisdk/dlls/DotNetZip.dll
andisdk/dlls/ExcelNumberFormat.dll
andisdk/dlls/FastColoredTextBox.dll
andisdk/dlls/Grpc.Core.Api.dll
andisdk/dlls/Grpc.Core.dll
andisdk/dlls/HtmlAgilityPack.dll
andisdk/dlls/IronPython.Modules.dll
andisdk/dlls/IronPython.SQLite.dll
andisdk/dlls/IronPython.Wpf.dll
andisdk/dlls/IronPython.dll
andisdk/dlls/MQTTnet.dll
andisdk/dlls/MathParser.org-mXparser.dll
andisdk/dlls/Microsoft.Bcl.AsyncInterfaces.dll
andisdk/dlls/Microsoft.Bcl.HashCode.dll
andisdk/dlls/Microsoft.Data.Sqlite.dll
andisdk/dlls/Microsoft.DotNet.PlatformAbstractions.dll
andisdk/dlls/Microsoft.Dynamic.dll
andisdk/dlls/Microsoft.EntityFrameworkCore.Abstractions.dll
andisdk/dlls/Microsoft.EntityFrameworkCore.Relational.dll
andisdk/dlls/Microsoft.EntityFrameworkCore.Sqlite.dll
andisdk/dlls/Microsoft.EntityFrameworkCore.dll
andisdk/dlls/Microsoft.Extensions.Caching.Abstractions.dll
andisdk/dlls/Microsoft.Extensions.Caching.Memory.dll
andisdk/dlls/Microsoft.Extensions.Configuration.Abstractions.dll
andisdk/dlls/Microsoft.Extensions.Configuration.Binder.dll
andisdk/dlls/Microsoft.Extensions.Configuration.dll
andisdk-2.2.1.dist-info/licenses/LICENSE
andisdk-2.2.1.dist-info/METADATA
andisdk-2.2.1.dist-info/WHEEL
andisdk-2.2.1.dist-info/entry_points.txt
andisdk-2.2.1.dist-info/top_level.txt
andisdk-2.2.1.dist-info/RECORD
