Metadata-Version: 2.4
Name: andisdk
Version: 2.2.1
Summary: ANDi python package to interact with ANDi scripting features from stand alone python package
Author: Technica Engineering
Classifier: Programming Language :: Python
Classifier: Programming Language :: Python :: 3
Classifier: Operating System :: Microsoft :: Windows
Classifier: Operating System :: POSIX :: Linux
Requires-Python: >=3.0.0
License-File: LICENSE
Requires-Dist: clr-loader>=0.2.5
Requires-Dist: pythonnet>=3.0.1
Requires-Dist: udsoncan>=1.14
Requires-Dist: rich>=11.2
Requires-Dist: lxml>=4.9.1
Requires-Dist: canmatrix>=0.9.5
Requires-Dist: ldfparser>=0.14.0
Requires-Dist: python-can>=4.2.2
Dynamic: author
Dynamic: classifier
Dynamic: description
Dynamic: description-content-type
Dynamic: license-file
Dynamic: requires-dist
Dynamic: requires-python
Dynamic: summary
